openleveldb/__init__.py
openleveldb/backend/__init__.py
openleveldb/backend/config.py
openleveldb/backend/connectorclient.py
openleveldb/backend/connectorcommon.py
openleveldb/backend/connectorlocal.py
openleveldb/backend/serializer.py
openleveldb/backend/server.py
openleveldb/database.py
openleveldb-0.1.5.dist-info/LICENSE
openleveldb-0.1.5.dist-info/WHEEL
openleveldb-0.1.5.dist-info/METADATA
openleveldb-0.1.5.dist-info/RECORD
