Metadata-Version: 2.1
Name: openleveldb
Version: 0.1.5
Summary: 
Home-page: https://github.com/lucmos/openleveldb
License: MIT
Keywords: leveldb,multiprocessing
Author: Luca Moschella
Author-email: luca.moschella94@gmail.com
Requires-Python: >=3.7.5,<4.0.0
Classifier: License :: OSI Approved :: MIT License
Classifier: Programming Language :: Python :: 3
Classifier: Programming Language :: Python :: 3.8
Classifier: Programming Language :: Python :: 3.9
Requires-Dist: flask (>=1.1.1,<2.0.0)
Requires-Dist: numpy (>=1.18.1,<2.0.0)
Requires-Dist: plyvel (>=1.1.0,<2.0.0)
Requires-Dist: pytest (>=5.4.1,<6.0.0)
Requires-Dist: python-dotenv (>=0.10.3,<0.11.0)
Requires-Dist: python-rapidjson (>=0.9.1,<0.10.0)
Requires-Dist: requests (>=2.22.0,<3.0.0)
Project-URL: Documentation, https://openleveldb.readthedocs.io/en/latest/index.html#
Project-URL: Repository, https://github.com/lucmos/openleveldb
